LICENSE
MANIFEST.in
README.md
flask_runner.py
setup.py
Flask_Runner.egg-info/PKG-INFO
Flask_Runner.egg-info/SOURCES.txt
Flask_Runner.egg-info/dependency_links.txt
Flask_Runner.egg-info/not-zip-safe
Flask_Runner.egg-info/requires.txt
Flask_Runner.egg-info/top_level.txt