Metadata-Version: 1.0
Name: Flask-Runner
Version: 2.0.2
Summary: A set of standard command line arguments for Flask applications built on top of Flask-Script
Home-page: http://github.com/miguelgrinberg/flask-runner/
Author: Miguel Grinberg
Author-email: miguelgrinberg50@gmail.com
License: BSD
Platform: any
Classifier: Environment :: Web Environment
Classifier: Intended Audience :: Developers
Classifier: License :: OSI Approved :: BSD License
Classifier: Operating System :: OS Independent
Classifier: Programming Language :: Python
Classifier: Topic :: Internet :: WWW/HTTP :: Dynamic Content
Classifier: Topic :: Software Development :: Libraries :: Python Modules
